zensical/__init__.py
zensical-0.0.2.dist-info/METADATA
zensical-0.0.2.dist-info/WHEEL
zensical-0.0.2.dist-info/RECORD
