Metadata-Version: 2.4
Name: zensical
Version: 0.0.2
Summary: Zensical CLI
Project-URL: Source, https://github.com/zensical/zensical
License: MIT
